algovision/__init__.py
algovision/conditions.py
algovision/control_structures.py
algovision/core.py
algovision/functions.py
algovision/instructions.py
algovision-0.1.2.dist-info/LICENSE
algovision-0.1.2.dist-info/METADATA
algovision-0.1.2.dist-info/WHEEL
algovision-0.1.2.dist-info/top_level.txt
algovision-0.1.2.dist-info/RECORD
