Metadata-Version: 2.1
Name: algovision
Version: 0.1.2
Summary: AlgoVision - A Framework for Differentiable Algorithms and Algorithmic Supervision
Home-page: https://github.com/Felix-Petersen/algovision
Author: Felix Petersen
Author-email: ads0399@felix-petersen.de
License: MIT License
Classifier: Programming Language :: Python :: 3
Classifier: License :: OSI Approved :: MIT License
Classifier: Operating System :: OS Independent
Classifier: Topic :: Scientific/Engineering
Classifier: Topic :: Scientific/Engineering :: Mathematics
Classifier: Topic :: Scientific/Engineering :: Artificial Intelligence
Classifier: Topic :: Software Development
Classifier: Topic :: Software Development :: Libraries
Classifier: Topic :: Software Development :: Libraries :: Python Modules
Requires-Python: >=3.6
License-File: LICENSE
Requires-Dist: numpy
Requires-Dist: torch (>=1.9.0)
